tokenmanager/__init__.py
tokenmanager/__main__.py
tokenmanager-0.0.1.dist-info/DESCRIPTION.rst
tokenmanager-0.0.1.dist-info/METADATA
tokenmanager-0.0.1.dist-info/RECORD
tokenmanager-0.0.1.dist-info/WHEEL
tokenmanager-0.0.1.dist-info/metadata.json
tokenmanager-0.0.1.dist-info/top_level.txt
