Metadata-Version: 2.0
Name: tokenmanager
Version: 0.0.1
Summary: Simple token manager for token-based REST APIs
Home-page: https://bitbucket.org/dogwynn/tokenmanager
Author: David O'Gwynn
Author-email: dogywnn@acm.org
License: BSD
Keywords: token manager rest api development helper utility
Platform: UNKNOWN
Classifier: Development Status :: 3 - Alpha
Classifier: Intended Audience :: Developers
Classifier: License :: OSI Approved :: BSD License
Classifier: Programming Language :: Python :: 3
Requires-Dist: gems
Requires-Dist: ruamel.yaml
